polylx/__init__.py
polylx/core.py
polylx/plots.py
polylx/reports.py
polylx/shell.py
polylx/utils.py
polylx/example/fracs.cpg
polylx/example/fracs.dbf
polylx/example/fracs.prj
polylx/example/fracs.shp
polylx/example/fracs.shx
polylx/example/sg2.cpg
polylx/example/sg2.dbf
polylx/example/sg2.shp
polylx/example/sg2.shx
polylx/example/test10.dbf
polylx/example/test10.shp
polylx/example/test10.shx
polylx-0.6.1.dist-info/METADATA
polylx-0.6.1.dist-info/WHEEL
polylx-0.6.1.dist-info/entry_points.txt
polylx-0.6.1.dist-info/licenses/LICENSE
polylx-0.6.1.dist-info/RECORD
