Metadata-Version: 2.4
Name: polylx
Version: 0.6.1
Summary: A Python package to visualize and analyze microstructures
Project-URL: Homepage, https://github.com/ondrolexa/polylx
Project-URL: Documentation, https://polylx.readthedocs.io/
Project-URL: Repository, https://github.com/ondrolexa/polylx.git
Project-URL: Issues, https://github.com/ondrolexa/polylx/issues
Project-URL: Changelog, https://github.com/ondrolexa/polylx/blob/master/CHANGELOG.md
Author-email: Ondrej Lexa <lexa.ondrej@gmail.com>
Maintainer-email: Ondrej Lexa <lexa.ondrej@gmail.com>
License-Expression: MIT
License-File: LICENSE
Keywords: geology,microstructures
Classifier: Development Status :: 4 - Beta
Classifier: Intended Audience :: Science/Research
Classifier: License :: OSI Approved :: MIT License
Classifier: Programming Language :: Python :: 3
Classifier: Programming Language :: Python :: 3.10
Requires-Python: >=3.10
Requires-Dist: fiona
Requires-Dist: jenkspy
Requires-Dist: matplotlib
Requires-Dist: networkx
Requires-Dist: numpy
Requires-Dist: pandas
Requires-Dist: pyarrow
Requires-Dist: pyefd
Requires-Dist: pyshp
Requires-Dist: scipy
Requires-Dist: seaborn
Requires-Dist: shapely
Requires-Dist: shapelysmooth
Provides-Extra: dev
Requires-Dist: black; extra == 'dev'
Requires-Dist: ipykernel; extra == 'dev'
Requires-Dist: jupyterlab; extra == 'dev'
Requires-Dist: nbsphinx; extra == 'dev'
Requires-Dist: nbsphinx-link; extra == 'dev'
Requires-Dist: nbval; extra == 'dev'
Requires-Dist: pytest; extra == 'dev'
Requires-Dist: sphinx; extra == 'dev'
Requires-Dist: sphinx-mdinclude; extra == 'dev'
Requires-Dist: sphinx-rtd-theme; extra == 'dev'
Provides-Extra: docs
Requires-Dist: ipykernel; extra == 'docs'
Requires-Dist: nbsphinx; extra == 'docs'
Requires-Dist: nbsphinx-link; extra == 'docs'
Requires-Dist: sphinx; extra == 'docs'
Requires-Dist: sphinx-mdinclude; extra == 'docs'
Requires-Dist: sphinx-rtd-theme; extra == 'docs'
Provides-Extra: extra
Requires-Dist: jupyterlab; extra == 'extra'
Provides-Extra: tests
Requires-Dist: nbval; extra == 'tests'
Requires-Dist: pytest; extra == 'tests'
